mylib/__init__.py
mylib/function.py
mylibTech-0.1.0.dist-info/METADATA
mylibTech-0.1.0.dist-info/WHEEL
mylibTech-0.1.0.dist-info/top_level.txt
mylibTech-0.1.0.dist-info/RECORD
